go_project_cli/__init__.py
go_project_cli/examples/example.py
go_project_cli/main.py
go_project_cli/utils.py
go_project_cli-0.3.0.dist-info/LICENSE
go_project_cli-0.3.0.dist-info/METADATA
go_project_cli-0.3.0.dist-info/WHEEL
go_project_cli-0.3.0.dist-info/entry_points.txt
go_project_cli-0.3.0.dist-info/RECORD
