Metadata-Version: 2.1
Name: go-project-cli
Version: 0.3.0
Summary: 
License: MIT
Author: sangjinsu
Author-email: climbplant39@kakao.com
Requires-Python: >=3.9,<4.0
Classifier: License :: OSI Approved :: MIT License
Classifier: Programming Language :: Python :: 3
Classifier: Programming Language :: Python :: 3.9
Classifier: Programming Language :: Python :: 3.10
Classifier: Programming Language :: Python :: 3.11
Requires-Dist: typer[all] (>=0.9.0,<0.10.0)
